abcount/__init__.py
abcount/_definitions.py
abcount/_logging.py
abcount/config.py
abcount/components/__init__.py
abcount/components/classifier.py
abcount/components/common.py
abcount/components/counter.py
abcount/components/ions.py
abcount/components/isoelectric.py
abcount/components/smarts.py
abcount/data/acid_definitions.json
abcount/data/base_definitions.json
abcount/data/raw_definitions.json
abcount/model/classifier.py
abcount/model/common.py
abcount/model/counter.py
abcount/model/ions.py
abcount/model/isoelectric.py
abcount-0.2.9.dist-info/licenses/LICENSE
abcount-0.2.9.dist-info/METADATA
abcount-0.2.9.dist-info/WHEEL
abcount-0.2.9.dist-info/top_level.txt
abcount-0.2.9.dist-info/RECORD
