Metadata-Version: 2.4
Name: abcount
Version: 0.2.9
Summary: Extended cheminformatics package to work with acidic and basic groups in molecules.
Requires-Python: >=3.10
License-File: LICENSE
Requires-Dist: rdkit
Requires-Dist: dataclasses_json
Dynamic: license-file
